easy_class/__init__.py
easy_class/base.py
easy_class/choices.py
easy_class/fields.py
easy_class-1.1.2.dist-info/DESCRIPTION.rst
easy_class-1.1.2.dist-info/entry_points.txt
easy_class-1.1.2.dist-info/METADATA
easy_class-1.1.2.dist-info/metadata.json
easy_class-1.1.2.dist-info/RECORD
easy_class-1.1.2.dist-info/top_level.txt
easy_class-1.1.2.dist-info/WHEEL
